datasette_checkbox/__init__.py
datasette_checkbox-0.1a4.dist-info/licenses/LICENSE
datasette_checkbox-0.1a4.dist-info/METADATA
datasette_checkbox-0.1a4.dist-info/WHEEL
datasette_checkbox-0.1a4.dist-info/entry_points.txt
datasette_checkbox-0.1a4.dist-info/top_level.txt
datasette_checkbox-0.1a4.dist-info/RECORD
