Metadata-Version: 2.4
Name: datasette-checkbox
Version: 0.1a4
Summary: Add interactive checkboxes to columns in Datasette
Author: Simon Willison
License-Expression: Apache-2.0
Project-URL: Homepage, https://github.com/datasette/datasette-checkbox
Project-URL: Changelog, https://github.com/datasette/datasette-checkbox/releases
Project-URL: Issues, https://github.com/datasette/datasette-checkbox/issues
Project-URL: CI, https://github.com/datasette/datasette-checkbox/actions
Classifier: Framework :: Datasette
Requires-Python: >=3.10
License-File: LICENSE
Requires-Dist: datasette>=1.0a19
Provides-Extra: test
Requires-Dist: pytest; extra == "test"
Requires-Dist: pytest-asyncio; extra == "test"
Dynamic: license-file
